k256/__init__.py
k256/types/__init__.py
k256/types/blockhash.py
k256/types/fees.py
k256/types/heartbeat.py
k256/types/messages.py
k256/types/pool.py
k256/types/quote.py
k256/types/token.py
k256/utils/__init__.py
k256/utils/base58.py
k256/ws/__init__.py
k256/ws/client.py
k256/ws/decoder.py
k256_sdk-0.1.0.dist-info/METADATA
k256_sdk-0.1.0.dist-info/WHEEL
k256_sdk-0.1.0.dist-info/licenses/LICENSE
k256_sdk-0.1.0.dist-info/RECORD
