Metadata-Version: 2.4
Name: k256-sdk
Version: 0.1.0
Summary: Official Python SDK for K256 - the gateway to Solana's liquidity ecosystem
Project-URL: Homepage, https://k256.xyz
Project-URL: Documentation, https://docs.k256.xyz
Project-URL: Repository, https://github.com/k256-xyz/k256-sdks
Project-URL: Issues, https://github.com/k256-xyz/k256-sdks/issues
Project-URL: Changelog, https://github.com/k256-xyz/k256-sdks/releases
Author-email: K256 <support@k256.xyz>
Maintainer-email: K256 <support@k256.xyz>
License: MIT
License-File: LICENSE
Keywords: aggregator,blockchain,cryptocurrency,defi,dex,k256,solana,swap,trading,websocket
Classifier: Development Status :: 4 - Beta
Classifier: Intended Audience :: Developers
Classifier: License :: OSI Approved :: MIT License
Classifier: Operating System :: OS Independent
Classifier: Programming Language :: Python :: 3
Classifier: Programming Language :: Python :: 3.9
Classifier: Programming Language :: Python :: 3.10
Classifier: Programming Language :: Python :: 3.11
Classifier: Programming Language :: Python :: 3.12
Classifier: Programming Language :: Python :: 3.13
Classifier: Topic :: Internet :: WWW/HTTP
Classifier: Topic :: Office/Business :: Financial
Classifier: Topic :: Software Development :: Libraries :: Python Modules
Classifier: Typing :: Typed
Requires-Python: >=3.9
Requires-Dist: aiohttp>=3.9
Requires-Dist: pydantic>=2.0
Requires-Dist: websockets>=12.0
Provides-Extra: dev
Requires-Dist: mypy>=1.8; extra == 'dev'
Requires-Dist: pytest-asyncio>=0.23; extra == 'dev'
Requires-Dist: pytest>=8.0; extra == 'dev'
Requires-Dist: ruff>=0.2; extra == 'dev'
